fontbakery/__init__.py
fontbakery/__main__.py
fontbakery/_version.py
fontbakery/axes.proto
fontbakery/axes_pb2.py
fontbakery/callable.py
fontbakery/checkrunner.py
fontbakery/cli.py
fontbakery/codetesting.py
fontbakery/configuration.py
fontbakery/constants.py
fontbakery/designers.proto
fontbakery/designers_pb2.py
fontbakery/errors.py
fontbakery/fonts_profile.py
fontbakery/fonts_public.proto
fontbakery/fonts_public_pb2.py
fontbakery/glyphdata.py
fontbakery/legacy_checkids.py
fontbakery/message.py
fontbakery/prelude.py
fontbakery/profile.py
fontbakery/result.py
fontbakery/status.py
fontbakery/testable.py
fontbakery/update_shaping_tests.py
fontbakery/utils.py
fontbakery/checks/STAT_in_statics.py
fontbakery/checks/STAT_strings.py
fontbakery/checks/__init__.py
fontbakery/checks/alt_caron.py
fontbakery/checks/arabic_high_hamza.py
fontbakery/checks/arabic_spacing_symbols.py
fontbakery/checks/base_has_width.py
fontbakery/checks/caps_vertically_centered.py
fontbakery/checks/case_mapping.py
fontbakery/checks/cjk_chws_feature.py
fontbakery/checks/cjk_not_enough_glyphs.py
fontbakery/checks/color_cpal_brightness.py
fontbakery/checks/conditions.py
fontbakery/checks/contour_count.py
fontbakery/checks/control_chars.py
fontbakery/checks/designspace_has_consistent_codepoints.py
fontbakery/checks/designspace_has_consistent_glyphset.py
fontbakery/checks/designspace_has_consistent_groups.py
fontbakery/checks/designspace_has_default_master.py
fontbakery/checks/designspace_has_sources.py
fontbakery/checks/dotted_circle.py
fontbakery/checks/empty_glyph_on_gid1_for_colrv0.py
fontbakery/checks/empty_letters.py
fontbakery/checks/file_size.py
fontbakery/checks/fontbakery_version.py
fontbakery/checks/fontdata_namecheck.py
fontbakery/checks/fontvalidator.py
fontbakery/checks/freetype_rasterizer.py
fontbakery/checks/fvar_name_entries.py
fontbakery/checks/gpos7.py
fontbakery/checks/gpos_kerning_info.py
fontbakery/checks/hinting_impact.py
fontbakery/checks/inconsistencies_between_fvar_STAT.py
fontbakery-0.13.3.dist-info/licenses/AUTHORS.txt
fontbakery-0.13.3.dist-info/licenses/LICENSE.txt
fontbakery-0.13.3.dist-info/METADATA
fontbakery-0.13.3.dist-info/WHEEL
fontbakery-0.13.3.dist-info/entry_points.txt
fontbakery-0.13.3.dist-info/top_level.txt
fontbakery-0.13.3.dist-info/RECORD
