Metadata-Version: 2.4
Name: fontbakery
Version: 0.13.3
Summary: A font quality assurance tool for everyone
Author: Jens Kutilek, Lasse Fister, Marc Foley, Miguel Sousa, Nikolaus Waxweiler, Rosalie Wagner, Simon Cozens, Vitaly Volkov, Viviana Monsalve, Yanone
Author-email: Chris Simpkins <csimpkins@google.com>, Dave Crossland <dcrossland@google.com>, Felipe Sanches <juca@members.fsf.org>
Maintainer-email: Felipe Sanches <juca@members.fsf.org>
Requires-Python: >=3.9
License-File: LICENSE.txt
License-File: AUTHORS.txt
Requires-Dist: beziers==0.6.*,>=0.6.0
Requires-Dist: cmarkgfm>=0.4
Requires-Dist: defcon
Requires-Dist: dehinter>=3.1.0
Requires-Dist: fontTools[ufo]>=4.47.0
Requires-Dist: freetype-py<2.4.0
Requires-Dist: Jinja2>=3.0.0
Requires-Dist: munkres
Requires-Dist: opentypespec>=1.9.2
Requires-Dist: opentype-sanitizer==9.*,>=9.1.0
Requires-Dist: packaging>=14.5
Requires-Dist: pip-api
Requires-Dist: PyYAML
Requires-Dist: requests>=2.19
Requires-Dist: rich
Requires-Dist: toml
Requires-Dist: typing_extensions; python_version < "3.11"
Requires-Dist: ufolint
Requires-Dist: ufo2ft>=2.25.2
Requires-Dist: uharfbuzz
Requires-Dist: vharfbuzz>=0.2.0
Provides-Extra: beautifulsoup4
Requires-Dist: beautifulsoup4>=4.7.1; extra == "beautifulsoup4"
Provides-Extra: shaperglot
Requires-Dist: shaperglot==1.*,>=1.0.0a1; extra == "shaperglot"
Provides-Extra: googlefontsalwayslatest
Requires-Dist: axisregistry==0.4.*,>=0.4.12; extra == "googlefontsalwayslatest"
Requires-Dist: gflanguages==0.7.*,>=0.7.3; extra == "googlefontsalwayslatest"
Requires-Dist: gfsubsets>=2024.9.25; extra == "googlefontsalwayslatest"
Requires-Dist: glyphsets==1.*,>=1.1.0; extra == "googlefontsalwayslatest"
Requires-Dist: shaperglot==1.*,>=1.0.2; extra == "googlefontsalwayslatest"
Provides-Extra: adobefonts
Provides-Extra: fontval
Requires-Dist: lxml; extra == "fontval"
Provides-Extra: fontwerk
Requires-Dist: fontbakery[googlefonts]; extra == "fontwerk"
Provides-Extra: googlefonts
Requires-Dist: collidoscope>=0.5.2; extra == "googlefonts"
Requires-Dist: fonttools[lxml,unicode]; extra == "googlefonts"
Requires-Dist: protobuf<4,>=3.7.0; extra == "googlefonts"
Requires-Dist: stringbrewer; extra == "googlefonts"
Requires-Dist: unicodedata2; extra == "googlefonts"
Requires-Dist: fontbakery[beautifulsoup4]; extra == "googlefonts"
Requires-Dist: fontbakery[googlefontsalwayslatest]; extra == "googlefonts"
Requires-Dist: fontbakery[shaperglot]; extra == "googlefonts"
Provides-Extra: iso15008
Provides-Extra: microsoft
Provides-Extra: notofonts
Requires-Dist: fontbakery[googlefonts]; extra == "notofonts"
Provides-Extra: typenetwork
Requires-Dist: unicodedata2; extra == "typenetwork"
Requires-Dist: fontbakery[beautifulsoup4]; extra == "typenetwork"
Requires-Dist: fontbakery[shaperglot]; extra == "typenetwork"
Provides-Extra: docs
Requires-Dist: myst-parser==2.*,>=2.0.0; extra == "docs"
Requires-Dist: sphinx==7.1.*,>=7.1.2; extra == "docs"
Requires-Dist: sphinx_rtd_theme==2.*,>=2.0.0; extra == "docs"
Requires-Dist: m2r==0.3.*,>=0.3.1; extra == "docs"
Provides-Extra: all
Requires-Dist: fontbakery[docs]; extra == "all"
Requires-Dist: fontbakery[adobefonts]; extra == "all"
Requires-Dist: fontbakery[fontval]; extra == "all"
Requires-Dist: fontbakery[fontwerk]; extra == "all"
Requires-Dist: fontbakery[googlefonts]; extra == "all"
Requires-Dist: fontbakery[iso15008]; extra == "all"
Requires-Dist: fontbakery[notofonts]; extra == "all"
Requires-Dist: fontbakery[typenetwork]; extra == "all"
Provides-Extra: tests
Requires-Dist: black==23.12.1; extra == "tests"
Requires-Dist: pylint==3.0.3; extra == "tests"
Requires-Dist: pytest-cov==4.1.0; extra == "tests"
Requires-Dist: pytest-xdist==3.5.0; extra == "tests"
Requires-Dist: requests-mock==1.10.0; extra == "tests"
Requires-Dist: fontbakery[all]; extra == "tests"
Dynamic: license-file
